{
  "author": "peopleware",
  "dependencies": [],
  "description": "Sets the hostname to the certificate name.",
  "issues_url": "https://github.com/peopleware/puppet-hostname/issues",
  "license": "Apache-2.0",
  "name": "peopleware-hostname",
  "operatingsystem_support": [
    {
      "operatingsystem": "Debian",
      "operatingsystemrelease": [
        "7",
        "8",
        "9",
        "10"
      ]
    },
    {
      "operatingsystem": "Ubuntu",
      "operatingsystemrelease": [
        "14.04",
        "16.04",
        "18.04"
      ]
    }
  ],
  "project_page": "https://github.com/peopleware/puppet-hostname",
  "source": "https://github.com/peopleware/puppet-hostname",
  "summary": "Sets the hostname to the certificate name",
  "version": "0.0.3"
}
